learning/01_logic_gates/src/logic_gates.sv
module logic_gates (
    input logic a,
    input logic b,
    input logic [1:0] sel,

    output logic y
);

always_comb begin
    case (sel)
       2'b00 : y = a & b;
       2'b01 : y = a | b;
       2'b10 : y = a ^ b;
       2'b11 : y = ~a;
    endcase
end
   
   endmodule

learning/01_logic_gates/sim/logic_gates_tb.sv
module logic_gates_tb;
    logic a;
    logic b;
    logic [1:0] sel;
    logic y;

    logic_gates uut (
        .a(a),
        .b(b),
        .y(y),
        .sel(sel)
    );

    initial begin
        $dumpfile("waveform.vcd");
        $dumpvars(0, logic_gates_tb);

        $monitor("sel=%b a=%b b=%b y=%b", sel, a, b, y);
        sel = 00;
         a = 0;
         b = 0;
         #10;
         a = 0;
         b = 1;
         #10;
         a = 1;
         b = 0;
         #10;
         a = 1;
         b = 1;
         #10;

         sel = 01;
         a = 0;
         b = 0;
         #10;
         a = 0;
         b = 1;
         #10;
         a = 1;
         b = 0;
         #10;
         a = 1;
         b = 1;
         #10;

         sel = 10;
         a = 0;
         b = 0;
         #10;
         a = 0;
         b = 1;
         #10;
         a = 1;
         b = 0;
         #10;
         a = 1;
         b = 1;
         #10;

         sel = 11;
         a = 0;
         b = 0;
         #10;
         a = 0;
         b = 1;
         #10;
         a = 1;
         b = 0;
         #10;
         a = 1;
         b = 1;
         #10;

         $finish;


    end
endmodule

learning/01_logic_gates/sim/waveform.vcd
$date
	Wed Aug 19 23:55:44 2026
$end
$version
	Icarus Verilog
$end
$timescale
	1s
$end
$scope module logic_gates_tb $end
$var wire 1 ! y $end
$var reg 1 " a $end
$var reg 1 # b $end
$var reg 2 $ sel [1:0] $end
$scope module uut $end
$var wire 1 " a $end
$var wire 1 # b $end
$var wire 2 % sel [1:0] $end
$var reg 1 ! y $end
$upscope $end
$upscope $end
$enddefinitions $end
$comment Show the parameter values. $end
$dumpall
$end
#0
$dumpvars
b0 %
b0 $
0#
0"
0!
$end
#10
1#
#20
0#
1"
#30
1!
1#
#40
0!
0#
0"
b1 $
b1 %
#50
1!
1#
#60
0#
1"
#70
1#
#80
0!
0#
0"
b10 $
b10 %
#90
1!
1#
#100
0#
1"
#110
0!
1#
#120
1!
0#
0"
b11 $
b11 %
#130
1#
#140
0!
0#
1"
#150
1#
