learning/01_2bit_alu/src/2bit_alu.sv
module logic_gates (
    input logic [1:0] a,
    input logic [1:0] b,
    input logic [1:0] sel,

    output logic [1:0] y
);

always_comb begin
    case (sel)
       2'b00 : y = a + b;
       2'b01 : y = a - b;
       2'b10 : y = a & b;
       2'b11 : y = a ^ b;
    endcase
end
   
   endmodule

learning/01_2bit_alu/sim/2bit_alu_tb.sv
module logic_gates_tb;
    logic [1:0] a;
    logic [1:0] b;
    logic [1:0] sel;
    logic [1:0] y;

    logic_gates uut (
        .a(a),
        .b(b),
        .y(y),
        .sel(sel)
    );

    initial begin
        $dumpfile("waveform.vcd");
        $dumpvars(0, logic_gates_tb);

        $monitor("sel=%b a=%b b=%b y=%b", sel, a, b, y);
        
        for (int i = 0; i < 64; ++i) begin 
            {sel, a, b} = i;
            #10;
        end




//first attempt
        /*for(int i = 0; i<4; ++i) begin //loop through sel; traverse row
        sel=i;
            for (int j = 0; j < 16; j++) begin //loop through a b; traverse column; 2^4 cus 2 bits, two variables
                {a,b}=j;
                #10;
            end

        end*/



        /*sel = 00; //this in a nested for loop -> inner is 4, outer also 4; 2 bits
         a = 0;
         b = 0;
         #10;
         a = 0;
         b = 1;
         #10;
         a = 1;
         b = 0;
         #10;
         a = 1;
         b = 1;
         #10;

         sel = 01;
         a = 0;
         b = 0;
         #10;
         a = 0;
         b = 1;
         #10;
         a = 1;
         b = 0;
         #10;
         a = 1;
         b = 1;
         #10;

         sel = 10;
         a = 0;
         b = 0;
         #10;
         a = 0;
         b = 1;
         #10;
         a = 1;
         b = 0;
         #10;
         a = 1;
         b = 1;
         #10;

         sel = 11;
         a = 0;
         b = 0;
         #10;
         a = 0;
         b = 1;
         #10;
         a = 1;
         b = 0;
         #10;
         a = 1;
         b = 1;
         #10;*/

         $finish;


    end
endmodule

learning/01_2bit_alu/sim/waveform.vcd
$date
	Thu Aug 20 01:49:27 2026
$end
$version
	Icarus Verilog
$end
$timescale
	1s
$end
$scope module logic_gates_tb $end
$var wire 2 ! y [1:0] $end
$var reg 2 " a [1:0] $end
$var reg 2 # b [1:0] $end
$var reg 2 $ sel [1:0] $end
$scope module uut $end
$var wire 2 % a [1:0] $end
$var wire 2 & b [1:0] $end
$var wire 2 ' sel [1:0] $end
$var reg 2 ( y [1:0] $end
$upscope $end
$scope begin $ivl_for_loop0 $end
$var integer 32 ) i [31:0] $end
$upscope $end
$upscope $end
$enddefinitions $end
$comment Show the parameter values. $end
$dumpall
$end
#0
$dumpvars
b0 )
b0 (
b0 '
b0 &
b0 %
b0 $
b0 #
b0 "
b0 !
$end
#10
b1 !
b1 (
b1 #
b1 &
b1 )
#20
b10 !
b10 (
b10 #
b10 &
b10 )
#30
b11 !
b11 (
b11 #
b11 &
b11 )
#40
b1 !
b1 (
b1 "
b1 %
b0 #
b0 &
b100 )
#50
b10 !
b10 (
b1 #
b1 &
b101 )
#60
b11 !
b11 (
b10 #
b10 &
b110 )
#70
b0 !
b0 (
b11 #
b11 &
b111 )
#80
b10 !
b10 (
b10 "
b10 %
b0 #
b0 &
b1000 )
#90
b11 !
b11 (
b1 #
b1 &
b1001 )
#100
b0 !
b0 (
b10 #
b10 &
b1010 )
#110
b1 !
b1 (
b11 #
b11 &
b1011 )
#120
b11 !
b11 (
b11 "
b11 %
b0 #
b0 &
b1100 )
#130
b0 !
b0 (
b1 #
b1 &
b1101 )
#140
b1 !
b1 (
b10 #
b10 &
b1110 )
#150
b10 !
b10 (
b11 #
b11 &
b1111 )
#160
b0 !
b0 (
b1 $
b1 '
b0 "
b0 %
b0 #
b0 &
b10000 )
#170
b11 !
b11 (
b1 #
b1 &
b10001 )
#180
b10 !
b10 (
b10 #
b10 &
b10010 )
#190
b1 !
b1 (
b11 #
b11 &
b10011 )
#200
b1 "
b1 %
b0 #
b0 &
b10100 )
#210
b0 !
b0 (
b1 #
b1 &
b10101 )
#220
b11 !
b11 (
b10 #
b10 &
b10110 )
#230
b10 !
b10 (
b11 #
b11 &
b10111 )
#240
b10 "
b10 %
b0 #
b0 &
b11000 )
#250
b1 !
b1 (
b1 #
b1 &
b11001 )
#260
b0 !
b0 (
b10 #
b10 &
b11010 )
#270
b11 !
b11 (
b11 #
b11 &
b11011 )
#280
b11 "
b11 %
b0 #
b0 &
b11100 )
#290
b10 !
b10 (
b1 #
b1 &
b11101 )
#300
b1 !
b1 (
b10 #
b10 &
b11110 )
#310
b0 !
b0 (
b11 #
b11 &
b11111 )
#320
b10 $
b10 '
b0 "
b0 %
b0 #
b0 &
b100000 )
#330
b1 #
b1 &
b100001 )
#340
b10 #
b10 &
b100010 )
#350
b11 #
b11 &
b100011 )
#360
b1 "
b1 %
b0 #
b0 &
b100100 )
#370
b1 !
b1 (
b1 #
b1 &
b100101 )
#380
b0 !
b0 (
b10 #
b10 &
b100110 )
#390
b1 !
b1 (
b11 #
b11 &
b100111 )
#400
b0 !
b0 (
b10 "
b10 %
b0 #
b0 &
b101000 )
#410
b1 #
b1 &
b101001 )
#420
b10 !
b10 (
b10 #
b10 &
b101010 )
#430
b11 #
b11 &
b101011 )
#440
b0 !
b0 (
b11 "
b11 %
b0 #
b0 &
b101100 )
#450
b1 !
b1 (
b1 #
b1 &
b101101 )
#460
b10 !
b10 (
b10 #
b10 &
b101110 )
#470
b11 !
b11 (
b11 #
b11 &
b101111 )
#480
b0 !
b0 (
b11 $
b11 '
b0 "
b0 %
b0 #
b0 &
b110000 )
#490
b1 !
b1 (
b1 #
b1 &
b110001 )
#500
b10 !
b10 (
b10 #
b10 &
b110010 )
#510
b11 !
b11 (
b11 #
b11 &
b110011 )
#520
b1 !
b1 (
b1 "
b1 %
b0 #
b0 &
b110100 )
#530
b0 !
b0 (
b1 #
b1 &
b110101 )
#540
b11 !
b11 (
b10 #
b10 &
b110110 )
#550
b10 !
b10 (
b11 #
b11 &
b110111 )
#560
b10 "
b10 %
b0 #
b0 &
b111000 )
#570
b11 !
b11 (
b1 #
b1 &
b111001 )
#580
b0 !
b0 (
b10 #
b10 &
b111010 )
#590
b1 !
b1 (
b11 #
b11 &
b111011 )
#600
b11 !
b11 (
b11 "
b11 %
b0 #
b0 &
b111100 )
#610
b10 !
b10 (
b1 #
b1 &
b111101 )
#620
b1 !
b1 (
b10 #
b10 &
b111110 )
#630
b0 !
b0 (
b11 #
b11 &
b111111 )
#640
b1000000 )
