learning/03_fsm_trafficLight/src/fsm.sv
/*
* traffic light fsm
* inputs: clk, reset
* outputs: red,yellow,green; use enums
*/

module trafficLight_fsm (
    input logic clk,
    input logic reset,
    output logic [1:0] lightColor
);

//change to enum
    typedef enum bit [1:0] {
        RED = 2'b00,
        YELLOW = 2'b01,
        GREEN = 2'b10
    } trafficLight;
    trafficLight nextState,currentState;

    //flag for if reset
    //typedef enum bit {
    //    false = 1'b0, 
    //    true = 1'b1} 
    //resetFlag

    //output logic [1:0] lightColor
    /*logic output red,
    logic output yellow,
    logic output green*/

//change state based on clock edge
always_comb begin 
    //previous state
    case (currentState) 
        RED: begin
            lightColor = 2'b00; 
            nextState = YELLOW;
        end 
        YELLOW: begin 
            lightColor = 2'b01;
            nextState = GREEN;
        end
        GREEN: begin 
            lightColor = 2'b10;
            nextState = RED;
        end
        default: begin 
            lightColor = 2'b00;
            nextState = RED;
        end
    endcase
end

//check if reset pressed; if true -> go to state S0
always_ff @(posedge clk) begin 
    if (reset == 1'b1) begin
        //resetFlag = true;
        //output red
        //lightColor = 2'b00;
        currentState <= RED;
    end
    else begin
        //next state
        currentState <= nextState;

    end
end

endmodule

learning/03_fsm_trafficLight/sim/fsm_tb.sv
module trafficLight_fsm_tb;
    logic clk;
    logic reset;
    logic [1:0] lightColor;

    trafficLight_fsm uut (
        .clk(clk),
        .reset(reset),
        .lightColor(lightColor)
    );

    initial begin 
        $dumpfile("waveform.vcd");
        $dumpvars(0,trafficLight_fsm_tb);

        $monitor("clk = %b, reset = %b, lightColor = %b", clk, reset, lightColor);

        clk = 0;
        reset = 1;

        @(posedge clk);
        #10.1 reset = 0; //wait to prevent race conition

        for (int i = 0; i < 7; i++) begin 
            @(posedge clk); //next light color at edge
        end

        $finish;
    end
    always #10 clk = ~clk;
endmodule

learning/03_fsm_trafficLight/sim/waveform.vcd
$date
	Tue Sep  8 19:06:10 2026
$end
$version
	Icarus Verilog
$end
$timescale
	1s
$end
$scope module trafficLight_fsm_tb $end
$var wire 2 ! lightColor [1:0] $end
$var reg 1 " clk $end
$var reg 1 # reset $end
$scope module uut $end
$var wire 1 " clk $end
$var wire 1 # reset $end
$var reg 2 $ lightColor [1:0] $end
$var reg 2 % currentState [1:0] $end
$var reg 2 & nextState [1:0] $end
$upscope $end
$scope begin $ivl_for_loop0 $end
$var integer 32 ' i [31:0] $end
$upscope $end
$upscope $end
$enddefinitions $end
$comment Show the parameter values. $end
$dumpall
$end
#0
$dumpvars
b0 '
b1 &
b0 %
b0 $
1#
0"
b0 !
$end
#10
1"
#20
0#
0"
#30
b10 &
b1 !
b1 $
b1 %
b1 '
1"
#40
0"
#50
b0 &
b10 !
b10 $
b10 %
b10 '
1"
#60
0"
#70
b1 &
b0 !
b0 $
b0 %
b11 '
1"
#80
0"
#90
b10 &
b1 !
b1 $
b1 %
b100 '
1"
#100
0"
#110
b0 &
b10 !
b10 $
b10 %
b101 '
1"
#120
0"
#130
b1 &
b0 !
b0 $
b0 %
b110 '
1"
#140
0"
#150
b10 &
b1 !
b1 $
b1 %
b111 '
1"
