learning/02_4bit_comparator/src/4bit_comparator.sv
/*
* 4 bit comparator
* 2 inputs
* 3 outputs
*/

module comparator (
    input logic [3:0] a,
    input logic [3:0] b,

    output logic equal,
    output logic greater,
    output logic less
);

always_comb begin 
    if (a > b) begin 
        greater = 1;
        less = 0;
        equal = 0;
    end
    else if (a < b) begin 
        greater = 0;
        less = 1;
        equal = 0;
    end
    else  begin 
        greater = 0;
        less = 0;
        equal = 1;
    end
end

endmodule

learning/02_4bit_comparator/sim/4bit_comparator_tb.sv
module comparator_tb;
    logic [3:0] a;
    logic [3:0] b;
    logic equal;
    logic greater;
    logic less;
    
    comparator uut (
        .a(a),
        .b(b),
        .equal(equal),
        .greater(greater),
        .less(less)
    );

    initial begin 
        $dumpfile("waveform.vcd");
        $dumpvars(0, comparator_tb);

        $monitor("a=%b b=%b equal=%b greater=%b less=%b", a, b, equal, greater, less);

        for (int i = 0; i < 256; ++i) begin 
            {a,b} = i;
            #10;
        end
        $finish;
    end

endmodule

learning/02_4bit_comparator/sim/waveform.vcd
$date
	Tue Aug 25 16:13:34 2026
$end
$version
	Icarus Verilog
$end
$timescale
	1s
$end
$scope module comparator_tb $end
$var wire 1 ! less $end
$var wire 1 " greater $end
$var wire 1 # equal $end
$var reg 4 $ a [3:0] $end
$var reg 4 % b [3:0] $end
$scope module uut $end
$var wire 4 & a [3:0] $end
$var wire 4 ' b [3:0] $end
$var reg 1 # equal $end
$var reg 1 " greater $end
$var reg 1 ! less $end
$upscope $end
$scope begin $ivl_for_loop0 $end
$var integer 32 ( i [31:0] $end
$upscope $end
$upscope $end
$enddefinitions $end
$comment Show the parameter values. $end
$dumpall
$end
#0
$dumpvars
b0 (
b0 '
b0 &
b0 %
b0 $
1#
0"
0!
$end
#10
0#
1!
b1 %
b1 '
b1 (
#20
b10 %
b10 '
b10 (
#30
b11 %
b11 '
b11 (
#40
b100 %
b100 '
b100 (
#50
b101 %
b101 '
b101 (
#60
b110 %
b110 '
b110 (
#70
b111 %
b111 '
b111 (
#80
b1000 %
b1000 '
b1000 (
#90
b1001 %
b1001 '
b1001 (
#100
b1010 %
b1010 '
b1010 (
#110
b1011 %
b1011 '
b1011 (
#120
b1100 %
b1100 '
b1100 (
#130
b1101 %
b1101 '
b1101 (
#140
b1110 %
b1110 '
b1110 (
#150
b1111 %
b1111 '
b1111 (
#160
0!
1"
b1 $
b1 &
b0 %
b0 '
b10000 (
#170
1#
0"
b1 %
b1 '
b10001 (
#180
0#
1!
b10 %
b10 '
b10010 (
#190
b11 %
b11 '
b10011 (
#200
b100 %
b100 '
b10100 (
#210
b101 %
b101 '
b10101 (
#220
b110 %
b110 '
b10110 (
#230
b111 %
b111 '
b10111 (
#240
b1000 %
b1000 '
b11000 (
#250
b1001 %
b1001 '
b11001 (
#260
b1010 %
b1010 '
b11010 (
#270
b1011 %
b1011 '
b11011 (
#280
b1100 %
b1100 '
b11100 (
#290
b1101 %
b1101 '
b11101 (
#300
b1110 %
b1110 '
b11110 (
#310
b1111 %
b1111 '
b11111 (
#320
0!
1"
b10 $
b10 &
b0 %
b0 '
b100000 (
#330
b1 %
b1 '
b100001 (
#340
1#
0"
b10 %
b10 '
b100010 (
#350
0#
1!
b11 %
b11 '
b100011 (
#360
b100 %
b100 '
b100100 (
#370
b101 %
b101 '
b100101 (
#380
b110 %
b110 '
b100110 (
#390
b111 %
b111 '
b100111 (
#400
b1000 %
b1000 '
b101000 (
#410
b1001 %
b1001 '
b101001 (
#420
b1010 %
b1010 '
b101010 (
#430
b1011 %
b1011 '
b101011 (
#440
b1100 %
b1100 '
b101100 (
#450
b1101 %
b1101 '
b101101 (
#460
b1110 %
b1110 '
b101110 (
#470
b1111 %
b1111 '
b101111 (
#480
0!
1"
b11 $
b11 &
b0 %
b0 '
b110000 (
#490
b1 %
b1 '
b110001 (
#500
b10 %
b10 '
b110010 (
#510
1#
0"
b11 %
b11 '
b110011 (
#520
0#
1!
b100 %
b100 '
b110100 (
#530
b101 %
b101 '
b110101 (
#540
b110 %
b110 '
b110110 (
#550
b111 %
b111 '
b110111 (
#560
b1000 %
b1000 '
b111000 (
#570
b1001 %
b1001 '
b111001 (
#580
b1010 %
b1010 '
b111010 (
#590
b1011 %
b1011 '
b111011 (
#600
b1100 %
b1100 '
b111100 (
#610
b1101 %
b1101 '
b111101 (
#620
b1110 %
b1110 '
b111110 (
#630
b1111 %
b1111 '
b111111 (
#640
0!
1"
b100 $
b100 &
b0 %
b0 '
b1000000 (
#650
b1 %
b1 '
b1000001 (
#660
b10 %
b10 '
b1000010 (
#670
b11 %
b11 '
b1000011 (
#680
1#
0"
b100 %
b100 '
b1000100 (
#690
0#
1!
b101 %
b101 '
b1000101 (
#700
b110 %
b110 '
b1000110 (
#710
b111 %
b111 '
b1000111 (
#720
b1000 %
b1000 '
b1001000 (
#730
b1001 %
b1001 '
b1001001 (
#740
b1010 %
b1010 '
b1001010 (
#750
b1011 %
b1011 '
b1001011 (
#760
b1100 %
b1100 '
b1001100 (
#770
b1101 %
b1101 '
b1001101 (
#780
b1110 %
b1110 '
b1001110 (
#790
b1111 %
b1111 '
b1001111 (
#800
0!
1"
b101 $
b101 &
b0 %
b0 '
b1010000 (
#810
b1 %
b1 '
b1010001 (
#820
b10 %
b10 '
b1010010 (
#830
b11 %
b11 '
b1010011 (
#840
b100 %
b100 '
b1010100 (
#850
1#
0"
b101 %
b101 '
b1010101 (
#860
0#
1!
b110 %
b110 '
b1010110 (
#870
b111 %
b111 '
b1010111 (
#880
b1000 %
b1000 '
b1011000 (
#890
b1001 %
b1001 '
b1011001 (
#900
b1010 %
b1010 '
b1011010 (
#910
b1011 %
b1011 '
b1011011 (
#920
b1100 %
b1100 '
b1011100 (
#930
b1101 %
b1101 '
b1011101 (
#940
b1110 %
b1110 '
b1011110 (
#950
b1111 %
b1111 '
b1011111 (
#960
0!
1"
b110 $
b110 &
b0 %
b0 '
b1100000 (
#970
b1 %
b1 '
b1100001 (
#980
b10 %
b10 '
b1100010 (
#990
b11 %
b11 '
b1100011 (
#1000
b100 %
b100 '
b1100100 (
#1010
b101 %
b101 '
b1100101 (
#1020
1#
0"
b110 %
b110 '
b1100110 (
#1030
0#
1!
b111 %
b111 '
b1100111 (
#1040
b1000 %
b1000 '
b1101000 (
#1050
b1001 %
b1001 '
b1101001 (
#1060
b1010 %
b1010 '
b1101010 (
#1070
b1011 %
b1011 '
b1101011 (
#1080
b1100 %
b1100 '
b1101100 (
#1090
b1101 %
b1101 '
b1101101 (
#1100
b1110 %
b1110 '
b1101110 (
#1110
b1111 %
b1111 '
b1101111 (
#1120
0!
1"
b111 $
b111 &
b0 %
b0 '
b1110000 (
#1130
b1 %
b1 '
b1110001 (
#1140
b10 %
b10 '
b1110010 (
#1150
b11 %
b11 '
b1110011 (
#1160
b100 %
b100 '
b1110100 (
#1170
b101 %
b101 '
b1110101 (
#1180
b110 %
b110 '
b1110110 (
#1190
1#
0"
b111 %
b111 '
b1110111 (
#1200
0#
1!
b1000 %
b1000 '
b1111000 (
#1210
b1001 %
b1001 '
b1111001 (
#1220
b1010 %
b1010 '
b1111010 (
#1230
b1011 %
b1011 '
b1111011 (
#1240
b1100 %
b1100 '
b1111100 (
#1250
b1101 %
b1101 '
b1111101 (
#1260
b1110 %
b1110 '
b1111110 (
#1270
b1111 %
b1111 '
b1111111 (
#1280
0!
1"
b1000 $
b1000 &
b0 %
b0 '
b10000000 (
#1290
b1 %
b1 '
b10000001 (
#1300
b10 %
b10 '
b10000010 (
#1310
b11 %
b11 '
b10000011 (
#1320
b100 %
b100 '
b10000100 (
#1330
b101 %
b101 '
b10000101 (
#1340
b110 %
b110 '
b10000110 (
#1350
b111 %
b111 '
b10000111 (
#1360
1#
0"
b1000 %
b1000 '
b10001000 (
#1370
0#
1!
b1001 %
b1001 '
b10001001 (
#1380
b1010 %
b1010 '
b10001010 (
#1390
b1011 %
b1011 '
b10001011 (
#1400
b1100 %
b1100 '
b10001100 (
#1410
b1101 %
b1101 '
b10001101 (
#1420
b1110 %
b1110 '
b10001110 (
#1430
b1111 %
b1111 '
b10001111 (
#1440
0!
1"
b1001 $
b1001 &
b0 %
b0 '
b10010000 (
#1450
b1 %
b1 '
b10010001 (
#1460
b10 %
b10 '
b10010010 (
#1470
b11 %
b11 '
b10010011 (
#1480
b100 %
b100 '
b10010100 (
#1490
b101 %
b101 '
b10010101 (
#1500
b110 %
b110 '
b10010110 (
#1510
b111 %
b111 '
b10010111 (
#1520
b1000 %
b1000 '
b10011000 (
#1530
1#
0"
b1001 %
b1001 '
b10011001 (
#1540
0#
1!
b1010 %
b1010 '
b10011010 (
#1550
b1011 %
b1011 '
b10011011 (
#1560
b1100 %
b1100 '
b10011100 (
#1570
b1101 %
b1101 '
b10011101 (
#1580
b1110 %
b1110 '
b10011110 (
#1590
b1111 %
b1111 '
b10011111 (
#1600
0!
1"
b1010 $
b1010 &
b0 %
b0 '
b10100000 (
#1610
b1 %
b1 '
b10100001 (
#1620
b10 %
b10 '
b10100010 (
#1630
b11 %
b11 '
b10100011 (
#1640
b100 %
b100 '
b10100100 (
#1650
b101 %
b101 '
b10100101 (
#1660
b110 %
b110 '
b10100110 (
#1670
b111 %
b111 '
b10100111 (
#1680
b1000 %
b1000 '
b10101000 (
#1690
b1001 %
b1001 '
b10101001 (
#1700
1#
0"
b1010 %
b1010 '
b10101010 (
#1710
0#
1!
b1011 %
b1011 '
b10101011 (
#1720
b1100 %
b1100 '
b10101100 (
#1730
b1101 %
b1101 '
b10101101 (
#1740
b1110 %
b1110 '
b10101110 (
#1750
b1111 %
b1111 '
b10101111 (
#1760
0!
1"
b1011 $
b1011 &
b0 %
b0 '
b10110000 (
#1770
b1 %
b1 '
b10110001 (
#1780
b10 %
b10 '
b10110010 (
#1790
b11 %
b11 '
b10110011 (
#1800
b100 %
b100 '
b10110100 (
#1810
b101 %
b101 '
b10110101 (
#1820
b110 %
b110 '
b10110110 (
#1830
b111 %
b111 '
b10110111 (
#1840
b1000 %
b1000 '
b10111000 (
#1850
b1001 %
b1001 '
b10111001 (
#1860
b1010 %
b1010 '
b10111010 (
#1870
1#
0"
b1011 %
b1011 '
b10111011 (
#1880
0#
1!
b1100 %
b1100 '
b10111100 (
#1890
b1101 %
b1101 '
b10111101 (
#1900
b1110 %
b1110 '
b10111110 (
#1910
b1111 %
b1111 '
b10111111 (
#1920
0!
1"
b1100 $
b1100 &
b0 %
b0 '
b11000000 (
#1930
b1 %
b1 '
b11000001 (
#1940
b10 %
b10 '
b11000010 (
#1950
b11 %
b11 '
b11000011 (
#1960
b100 %
b100 '
b11000100 (
#1970
b101 %
b101 '
b11000101 (
#1980
b110 %
b110 '
b11000110 (
#1990
b111 %
b111 '
b11000111 (
#2000
b1000 %
b1000 '
b11001000 (
#2010
b1001 %
b1001 '
b11001001 (
#2020
b1010 %
b1010 '
b11001010 (
#2030
b1011 %
b1011 '
b11001011 (
#2040
1#
0"
b1100 %
b1100 '
b11001100 (
#2050
0#
1!
b1101 %
b1101 '
b11001101 (
#2060
b1110 %
b1110 '
b11001110 (
#2070
b1111 %
b1111 '
b11001111 (
#2080
0!
1"
b1101 $
b1101 &
b0 %
b0 '
b11010000 (
#2090
b1 %
b1 '
b11010001 (
#2100
b10 %
b10 '
b11010010 (
#2110
b11 %
b11 '
b11010011 (
#2120
b100 %
b100 '
b11010100 (
#2130
b101 %
b101 '
b11010101 (
#2140
b110 %
b110 '
b11010110 (
#2150
b111 %
b111 '
b11010111 (
#2160
b1000 %
b1000 '
b11011000 (
#2170
b1001 %
b1001 '
b11011001 (
#2180
b1010 %
b1010 '
b11011010 (
#2190
b1011 %
b1011 '
b11011011 (
#2200
b1100 %
b1100 '
b11011100 (
#2210
1#
0"
b1101 %
b1101 '
b11011101 (
#2220
0#
1!
b1110 %
b1110 '
b11011110 (
#2230
b1111 %
b1111 '
b11011111 (
#2240
0!
1"
b1110 $
b1110 &
b0 %
b0 '
b11100000 (
#2250
b1 %
b1 '
b11100001 (
#2260
b10 %
b10 '
b11100010 (
#2270
b11 %
b11 '
b11100011 (
#2280
b100 %
b100 '
b11100100 (
#2290
b101 %
b101 '
b11100101 (
#2300
b110 %
b110 '
b11100110 (
#2310
b111 %
b111 '
b11100111 (
#2320
b1000 %
b1000 '
b11101000 (
#2330
b1001 %
b1001 '
b11101001 (
#2340
b1010 %
b1010 '
b11101010 (
#2350
b1011 %
b1011 '
b11101011 (
#2360
b1100 %
b1100 '
b11101100 (
#2370
b1101 %
b1101 '
b11101101 (
#2380
1#
0"
b1110 %
b1110 '
b11101110 (
#2390
0#
1!
b1111 %
b1111 '
b11101111 (
#2400
0!
1"
b1111 $
b1111 &
b0 %
b0 '
b11110000 (
#2410
b1 %
b1 '
b11110001 (
#2420
b10 %
b10 '
b11110010 (
#2430
b11 %
b11 '
b11110011 (
#2440
b100 %
b100 '
b11110100 (
#2450
b101 %
b101 '
b11110101 (
#2460
b110 %
b110 '
b11110110 (
#2470
b111 %
b111 '
b11110111 (
#2480
b1000 %
b1000 '
b11111000 (
#2490
b1001 %
b1001 '
b11111001 (
#2500
b1010 %
b1010 '
b11111010 (
#2510
b1011 %
b1011 '
b11111011 (
#2520
b1100 %
b1100 '
b11111100 (
#2530
b1101 %
b1101 '
b11111101 (
#2540
b1110 %
b1110 '
b11111110 (
#2550
1#
0"
b1111 %
b1111 '
b11111111 (
#2560
b100000000 (
