learning/04_fsm_overlappingSequenceDetector/src/overlappingSequenceDetectorFSM.sv
/*
* sequence detecotor fsm; overlapping; mealy machine
* inputs: clk, x
* outputs: sequenceDetected -> true
*/

module overlappingSequenceDetectorFSM(
    input logic clk,
    input logic x,
    input logic reset,
    
    output logic sequenceDetected
);

typedef enum bit [1:0] {
    S0 = 2'b00,
    S1 = 2'b01,
    S2 = 2'b10,
    S3 = 2'b11
    
} stateValues;
stateValues nextState, currentState;

always_comb begin
    case (currentState)
    S0: begin
        if (x==1'b1) begin
            nextState = S1;
            sequenceDetected = 1'b0;
        end
        else begin
            nextState = S0;
            sequenceDetected = 1'b0;
        end
    end
    S1: begin
        if (x == 1'b0) begin
            nextState = S2;
            sequenceDetected = 1'b0;
        end
        else begin
            nextState = S1;
            sequenceDetected = 1'b0;
        end
    end
    S2: begin
        if(x==1'b1) begin
            nextState = S3;
            sequenceDetected = 1'b0;
        end
        else begin
            nextState = S0;
            sequenceDetected = 1'b0;
        end
    end
    S3: begin
        if(x== 1'b1) begin
            nextState = S1;
            sequenceDetected = 1'b1;
        end
        else begin
            nextState = S2;
            sequenceDetected = 1'b0;
        end
    end
    default: begin
        /*if (reset == 1'b1) begin
            nextState = S0;
            sequenceDetected = 1'b0;
        end*/

        nextState = S0;
        sequenceDetected = 1'b0;
    end
    endcase
end

always_ff @(posedge clk) begin
    if (reset == 1'b1) begin
        currentState <= S0;
    end
    else begin
        currentState <= nextState;
    end
end

endmodule

learning/04_fsm_overlappingSequenceDetector/sim/overlappingSequenceDetectorFSM_tb.sv
//define signsls
//define dut
//create clock generator

/*send bit
 *  wait for clock edge
 *  set x 
 *  send to fsm
 */

/*initial block
 * iniitalize
 * asssert reset
 * directed tests
    sequence 1011

 * overlapping tests
 
 * random tests
 
 * setup for basys3
 finish*/

module overlappingSequenceDetector_tb;
logic clk;
logic reset;
logic x;
logic sequenceDetected;

logic test201,test202;

overlappingSequenceDetectorFSM uut (
    .clk(clk),
    .reset(reset),
    .x(x),
    .sequenceDetected(sequenceDetected)
);


initial begin
    clk = 0;
    reset = 1;
    x = 0;
end
always #10 clk = ~clk;
/*reset = 1;
x = 0;*/


initial begin
    $dumpfile ("waveform.vcd");
    $dumpvars(0,overlappingSequenceDetector_tb);
    $monitor("clk=%b,reset=%b,x=%b,sequenceDetected=%b",clk,reset,x,sequenceDetected);

//fed
    @(posedge clk);
        reset = 1;//start at S0
    @(negedge clk);
        reset = 0; 
        x = 1; //observe
    @(negedge clk);
        x=0;
    @(negedge clk);
        x=1;
    @(negedge clk);
        x=1;

//print if test worked
    @(posedge clk);
    #0.1
        if(sequenceDetected == 1'b1) begin
             $display ("PASS TEST 1");
        end
        else begin
            $display ("FAIL TEST 1");
        end
        
    //@(negedge clk)
    //    #10.001 reset = 0;
//feed bits
    //reset = 1;
    //reset = 0;

//overlapping
    @(posedge clk);
    #10.1 reset =1;
    @(negedge clk);
    reset = 0;
    x=1;
    @(negedge clk);
    x=0;
    @(negedge clk);
    x=1;
    @(negedge clk);
    x=1; //start of overlap

    @(posedge clk);
     #0.1
    if(sequenceDetected == 1'b1) begin
        $display ("\nPASS TEST 2.01\n");
        test201=1;
    end
    else begin
        $display ("\nFAIL TEST 2.01\n");
    end

    @(negedge clk);
    x=0;
    @(negedge clk);
    x=1;
    @(negedge clk);
    x=1;

    @(posedge clk);
    #0.1
    if(sequenceDetected == 1'b1) begin
        $display ("\nPASS TEST 2.02\n");
        test202=1;
    end
    else begin
        $display ("\nFAIL TEST 2.02\n");
    end
    //@(negedge clk);
    //x=0;

    @(posedge clk);
    #0.1
        if(test201 && test202 == 1) begin
             $display ("\nPASS TEST 2\n");
        end
        else begin
            $display ("\nFAIL TEST 2\n");
        end
    $finish;
end

endmodule

learning/04_fsm_overlappingSequenceDetector/sim/waveform.vcd
$date
	Thu Oct  1 09:34:57 2026
$end
$version
	Icarus Verilog
$end
$timescale
	1s
$end
$scope module overlappingSequenceDetector_tb $end
$var wire 1 ! sequenceDetected $end
$var reg 1 " clk $end
$var reg 1 # reset $end
$var reg 1 $ test201 $end
$var reg 1 % test202 $end
$var reg 1 & x $end
$scope module uut $end
$var wire 1 " clk $end
$var wire 1 # reset $end
$var wire 1 & x $end
$var reg 1 ! sequenceDetected $end
$var reg 2 ' currentState [1:0] $end
$var reg 2 ( nextState [1:0] $end
$upscope $end
$upscope $end
$enddefinitions $end
$comment Show the parameter values. $end
$dumpall
$end
#0
$dumpvars
b0 (
b0 '
0&
x%
x$
1#
0"
0!
$end
#10
1"
#20
b1 (
1&
0#
0"
#30
b1 '
1"
#40
b10 (
0&
0"
#50
b0 (
b10 '
1"
#60
b11 (
1&
0"
#70
1!
b1 (
b11 '
1"
#80
0"
#90
0!
b1 '
1"
#100
0"
#110
1"
#120
1#
0"
#130
b0 '
1"
#140
0#
0"
#150
b1 '
1"
#160
b10 (
0&
0"
#170
b0 (
b10 '
1"
#180
b11 (
1&
0"
#190
1!
b1 (
b11 '
1"
#200
0"
#210
0!
b1 '
1$
1"
#220
b10 (
0&
0"
#230
b0 (
b10 '
1"
#240
b11 (
1&
0"
#250
1!
b1 (
b11 '
1"
#260
0"
#270
0!
b1 '
1%
1"
